stac_fastapi/geoparquet/__init__.py
stac_fastapi/geoparquet/api.py
stac_fastapi/geoparquet/client.py
stac_fastapi/geoparquet/main.py
stac_fastapi/geoparquet/models.py
stac_fastapi/geoparquet/py.typed
stac_fastapi/geoparquet/search.py
stac_fastapi/geoparquet/settings.py
stac_fastapi_geoparquet-0.0.4.dist-info/licenses/LICENSE
stac_fastapi_geoparquet-0.0.4.dist-info/METADATA
stac_fastapi_geoparquet-0.0.4.dist-info/WHEEL
stac_fastapi_geoparquet-0.0.4.dist-info/top_level.txt
stac_fastapi_geoparquet-0.0.4.dist-info/RECORD
