Metadata-Version: 2.4
Name: stac-fastapi-geoparquet
Version: 0.0.4
Summary: A stac-fastapi implementation with a stac-geoparquet backend
Project-URL: Documentation, https://stac-utils.github.io/stac-fastapi-geoparquet
Project-URL: Github, https://github.com/stac-utils/stac-fastapi-geoparquet
Project-URL: Issues, https://github.com/stac-utils/stac-fastapi-geoparquet/issues
Project-URL: Changelog, https://github.com/stac-utils/stac-fastapi-geoparquet/blob/main/CHANGELOG.md
Classifier: Programming Language :: Python :: 3
Classifier: Programming Language :: Python :: 3.11
Classifier: Programming Language :: Python :: 3.12
Classifier: Programming Language :: Python :: 3.13
Classifier: Programming Language :: Python :: 3.14
Classifier: Development Status :: 1 - Planning
Requires-Python: >=3.11
License-File: LICENSE
Requires-Dist: attr>=0.3.2
Requires-Dist: fastapi>=0.115.8
Requires-Dist: geojson-pydantic>=1.2.0
Requires-Dist: obstore>=0.8.0
Requires-Dist: pydantic>=2.10.4
Requires-Dist: pystac>=1.13.0
Requires-Dist: rustac>=0.7.0
Requires-Dist: stac-fastapi-api>=5.0.2
Requires-Dist: stac-fastapi-extensions>=5.0.2
Requires-Dist: stac-fastapi-types>=5.0.2
Provides-Extra: lambda
Requires-Dist: mangum==0.20.0; extra == "lambda"
Provides-Extra: serve
Requires-Dist: uvicorn>=0.34.0; extra == "serve"
Dynamic: license-file
